args.py
constants.py
depgate.py
metapackage.py
analysis/__init__.py
analysis/heuristics.py
depgate-0.1.1.dist-info/licenses/LICENSE
depgate-0.1.1.dist-info/licenses/NOTICE
registry/__init__.py
registry/maven.py
registry/npm.py
registry/pypi.py
depgate-0.1.1.dist-info/METADATA
depgate-0.1.1.dist-info/WHEEL
depgate-0.1.1.dist-info/entry_points.txt
depgate-0.1.1.dist-info/top_level.txt
depgate-0.1.1.dist-info/RECORD
