Metadata-Version: 2.4
Name: depgate
Version: 0.1.1
Summary: DepGate detects and prevents dependency confusion and supply-chain risks. (Hard fork of Apiiro's Dependency Combobulator)
Author: cognitivegears
License: Apache-2.0
Project-URL: Homepage, https://github.com/cognitivegears/depgate
Project-URL: Bug Tracker, https://github.com/cognitivegears/depgate/issues
Project-URL: Upstream, https://github.com/apiiro/combobulator
Classifier: Programming Language :: Python :: 3
Classifier: License :: OSI Approved :: Apache Software License
Classifier: Operating System :: OS Independent
Requires-Python: >=3.8
License-File: LICENSE
License-File: NOTICE
Requires-Dist: requests<2.32.5,>=2.32.4
Requires-Dist: gql>=3.5.0
Requires-Dist: python-dotenv>=0.19.2
Requires-Dist: requirements-parser>=0.11.0
Dynamic: license-file
